sc_banker_acceptance_report/__init__.py
sc_banker_acceptance_report/main.py
sc_banker_acceptance_report/analyzer/__init__.py
sc_banker_acceptance_report/analyzer/ba_issuance_analyzer.py
sc_banker_acceptance_report/analyzer/base_analyzer.py
sc_banker_acceptance_report/summary/__init__.py
sc_banker_acceptance_report/summary/branch_summary_analyzer.py
sc_banker_acceptance_report/summary/manager_summary_analyzer.py
sc_banker_acceptance_report/tests/__init__.py
sc_banker_acceptance_report/tests/sample_config/production.yml
sc_banker_acceptance_report/utils/__init__.py
sc_banker_acceptance_report/utils/branch_utils.py
sc_banker_acceptance_report/utils/manifest_utils.py
sc_banker_acceptance_report-0.0.5.dist-info/licenses/LICENSE
sc_banker_acceptance_report-0.0.5.dist-info/METADATA
sc_banker_acceptance_report-0.0.5.dist-info/WHEEL
sc_banker_acceptance_report-0.0.5.dist-info/entry_points.txt
sc_banker_acceptance_report-0.0.5.dist-info/top_level.txt
sc_banker_acceptance_report-0.0.5.dist-info/RECORD
