Metadata-Version: 2.4
Name: sc-banker-acceptance-report
Version: 0.0.5
Summary: python project
Home-page: https://github.com/Scott-Lau/sc-banker-acceptance-report
Author: Scott Lau
Author-email: exceedego@126.com
License: MIT
Keywords: python
Platform: POSIX
Classifier: Programming Language :: Python :: 3
Classifier: Programming Language :: Python :: 3.6
Classifier: Programming Language :: Python :: 3.7
Classifier: Programming Language :: Python :: 3.8
Classifier: Programming Language :: Python :: 3.9
Classifier: Programming Language :: Python :: 3.10
Classifier: Programming Language :: Python :: 3.11
Classifier: Programming Language :: Python :: 3.12
Classifier: Programming Language :: Python :: 3.13
Classifier: License :: OSI Approved :: MIT License
Classifier: Operating System :: OS Independent
Classifier: Topic :: Software Development
Classifier: Topic :: Utilities
Requires-Python: >=3.6
License-File: LICENSE
Requires-Dist: sc-utilities>=0.0.11
Requires-Dist: sc-config>=0.0.15
Requires-Dist: sc-analyzer-base>=0.0.24
Requires-Dist: pandas>=1.3.2
Requires-Dist: numpy>=2.0.2
Requires-Dist: openpyxl>=3.0.7
Requires-Dist: xlrd>=2.0.1
Dynamic: author
Dynamic: author-email
Dynamic: classifier
Dynamic: description
Dynamic: home-page
Dynamic: keywords
Dynamic: license
Dynamic: license-file
Dynamic: platform
Dynamic: requires-dist
Dynamic: requires-python
Dynamic: summary
